{
 "color": "", 
 "taxonomy": "Clothing & Accessories/Women/Ethnic Wear/Sarees/Fashofreak Women's Georgette Saree (KRAZZY_2D_Pink)", 
 "site": "IN_amazon", 
 "currency": "INR", 
 "available_sizes": [], 
 "id": "938980633X", 
 "image_filename": "http://ecx.images-amazon.com/images/I/41KBkvdy3GL.jpg", 
 "style": "", 
 "fit": "", 
 "bestSellerRank": " #19 in Clothing & Accessories ( )", 
 "image_type": "look", 
 "review": [
  "Not the same product as shown in image", 
  "the colour on the promotion pic and the actual colour what I received is so contrast..its not like in the pic..Disappointed", 
  "it isfooling us it iswaste of money", 
  "Good saree", 
  "Saree is not at all as shown.not even  a single mark", 
  "Cancell my order", 
  "Good cloth quality and looking beautiful As per rate and its price is good....buy it without getting any doubt. ...", 
  "Dont  buy this product looking at picture given, its waste of money, iys not even georgette, 9885483124, what up me so that i can send correct pics of thos product."
 ], 
 "name": "Fashofreak Women's Georgette Saree (KRAZZY_2D_Pink)", 
 "details": [
  "-Fashofreak", 
  "- KRAZZY_2D"
 ], 
 "image_filename_all": {
  "front": [
   "http://ecx.images-amazon.com/images/I/41m29H6KggL.jpg"
  ], 
  "right": [
   "http://ecx.images-amazon.com/images/I/51WzD9Wp2qL.jpg", 
   "http://ecx.images-amazon.com/images/I/41WYNyMJZhL.jpg"
  ], 
  "look": [
   "http://ecx.images-amazon.com/images/I/41KBkvdy3GL.jpg"
  ], 
  "back": [
   "http://ecx.images-amazon.com/images/I/41RE2R53iHL.jpg"
  ], 
  "left": [
   "http://ecx.images-amazon.com/images/I/51I7boh8fdL.jpg"
  ]
 }, 
 "type": "", 
 "price": 199.0, 
 "brand": "Chigy Whigy", 
 "material": "", 
 "similar_items": [
  "http://www.amazon.in//SRP-Fashion-Selection-colour-saree/dp/B01KABDN7K?ie=UTF8&psc=1", 
  "http://www.amazon.in//Aashi-Sarees/dp/B01KCPU1V0?ie=UTF8&psc=1", 
  "http://www.amazon.in//SARGAM-FASHION-SARI/dp/B01JJ83FSW", 
  "http://www.amazon.in//Vivera-Womens-Silk-Saree-VRBGL_KABALI_Red/dp/B01JGH0OWG?ie=UTF8&psc=1", 
  "http://www.amazon.in//Sareeshop-Womens-Georgette-Saree-AaishaPink_Pink/dp/B01IF2ZH1Q?ie=UTF8&psc=1", 
  "http://www.amazon.in//SareeShop-Womens-Chiffon-Saree-Flower-814_Firozi/dp/B01IF2ZLR6?ie=UTF8&psc=1"
 ], 
 "reviewStars": [
  "1.0 out of 5 stars", 
  "2.0 out of 5 stars", 
  "1.0 out of 5 stars", 
  "2.0 out of 5 stars", 
  "1.0 out of 5 stars", 
  "1.0 out of 5 stars", 
  "4.0 out of 5 stars", 
  "1.0 out of 5 stars"
 ], 
 "model_worn": "yes", 
 "care": "", 
 "neck": "", 
 "url": "http://www.amazon.in/Fashofreak-Womens-Georgette-Saree-KRAZZY_2D_Pink/dp/938980633X", 
 "gender": "women", 
 "length": "", 
 "avgStars": [], 
 "image_url": "http://ecx.images-amazon.com/images/I/41KBkvdy3GL.jpg", 
 "sleeves": ""
}